<?xml version="1.0" encoding="UTF-8"?>
<!DOCTYPE tiles-definitions PUBLIC
        "-//Apache Software Foundation//DTD Tiles Configuration 3.0//EN"
        "http://tiles.apache.org/dtds/tiles-config_3_0.dtd">

<tiles-definitions>

	<definition name="kaltia" extends="viral">
		<put-attribute name="left" value="/WEB-INF/inicio/left.jsp" />
	</definition>
<!-- 	<definition name="perfilAdmin1" extends="kaltia"> -->
<!-- 		<put-attribute name="header" value="/modelo/viral/pages/viralHeaderInterno.jsp" /> -->
<!-- 		<put-attribute name="body" value="/modelo/viral/pages/accesoControl1.jsp" /> -->
<!-- 	</definition> -->
	<definition name="kaltiaMaquetas" extends="kaltia">
		<put-attribute name="header" value="/modelo/viral/pages/viralHeaderInterno.jsp" />
		<put-attribute name="body" value="/empresa/kaltia/pages/kaltiaMaquetas.jsp" />
		<put-attribute name="footer" value="/modelo/viral/pages/viralFooter.jsp" />
		<put-attribute name="head" value="/WEB-INF/inicio/head.jsp" />
		<put-attribute name="foot" value="/WEB-INF/inicio/foot.jsp" />
	</definition>
	
	<definition name="mazda" extends="bronea">
		<put-attribute name="empresa" value="Mazda" cascade="true" />
	</definition>	
	
		
<!-- 	<definition name="menuA" extends="bronea"> -->
<!-- 		<put-attribute name="left" value="/WEB-INF/inicio/left.jsp" /> -->
<!-- 		<put-attribute name="body" value="/WEB-INF/inicio/body.jsp" /> -->
<!-- 		<put-attribute name="footer" value="/WEB-INF/inicio/footer.jsp" /> -->

<!-- 	</definition> -->
	
	
<!-- 	<definition name="nosotros" extends="bronea"> -->
<!-- 		<put-attribute name="header" value="/modelo/bronea/pages/headerInterno.jsp" /> -->
<!-- 		<put-attribute name="body" value="/modelo/bronea/pages/nosotros.jsp" /> -->
<!-- 		<put-attribute name="footer" value="/WEB-INF/inicio/footer.jsp" /> -->
<!-- 		<put-attribute name="left" value="/WEB-INF/inicio/left.jsp" /> -->
<!-- 	</definition> -->
</tiles-definitions>